qldebugger/__init__.py
qldebugger/__main__.py
qldebugger/actions/__init__.py
qldebugger/actions/event_source_mapping.py
qldebugger/actions/infra.py
qldebugger/actions/lambda_.py
qldebugger/actions/message.py
qldebugger/aws.py
qldebugger/cli.py
qldebugger/config/__init__.py
qldebugger/config/file_parser.py
qldebugger/example/__init__.py
qldebugger/example/lambdas.py
qldebugger/py.typed
qldebugger-0.3.0.dist-info/LICENSE
qldebugger-0.3.0.dist-info/METADATA
qldebugger-0.3.0.dist-info/WHEEL
qldebugger-0.3.0.dist-info/entry_points.txt
qldebugger-0.3.0.dist-info/RECORD
